{
  "fetched_at": "2026-04-23T03:40:54.959Z",
  "origin": "url:https://arxiv.org/abs/2509.25149",
  "origin_url": "https://arxiv.org/abs/2509.25149",
  "fetcher": "opencli",
  "fetcher_reason": "domain-override",
  "content_sha": "66bf7e2e68645cdc390ff5cf2228aec9ca193f0b1518ba531ddaa2457ee9159c",
  "content_length": 2542,
  "quality_flags": [],
  "quality_status": "good",
  "images": [
    {
      "local": "images/img_001.png",
      "remote": "",
      "bytes": 640
    }
  ],
  "notes": [
    "opencli adapter: arxiv-web",
    "hirono post-processors: arxiv-strip-trailing-chrome, arxiv-structure-improve",
    "arxiv: truncated trailing chrome at line 43 (150 lines removed)",
    "arxiv: restructured (title + metadata + abstract only; dropped all trailing chrome)",
    "arxiv: collapsed 90-author list to 10 + summary",
    "1 images downloaded by adapter"
  ]
}
